pydemult/__init__.py
pydemult/buffered_reader.py
pydemult/mutationhash.py
pydemult/pydemult.py
pydemult/worker.py
pydemult-0.2.dist-info/DESCRIPTION.rst
pydemult-0.2.dist-info/METADATA
pydemult-0.2.dist-info/RECORD
pydemult-0.2.dist-info/WHEEL
pydemult-0.2.dist-info/entry_points.txt
pydemult-0.2.dist-info/metadata.json
pydemult-0.2.dist-info/top_level.txt
