Metadata-Version: 2.0
Name: pydemult
Version: 0.2
Summary: Streamed and parallel demultiplexing of fastq files in python
Home-page: https://github.com/jenzopr/pydemult
Author: Jens Preussner
Author-email: jens.preussner@mpi-bn.mpg.de
License: MIT
Platform: UNKNOWN
Classifier: License :: OSI Approved :: MIT License
Classifier: Intended Audience :: Science/Research
Classifier: Topic :: Scientific/Engineering :: Bio-Informatics
Classifier: Programming Language :: Python :: 3
Requires-Dist: pandas
Requires-Dist: mputil
